{
  "Usings": [
    "BlazeCommon",
    "NLog"
  ],
  "Namespace": "Blaze2SDK.Components",
  "Components": [
    {
      "Id": 22,
      "Name": "RegistrationComponent",
      "DefaultRequestType": "NullStruct",
      "DefaultResponseType": "NullStruct",
      "DefaultErrorType": "NullStruct",
      "ErrorEnum": "Blaze2RpcError",
      "Methods": [
        {
          "Id": 2,
          "Name": "check",
          "RequestType": "NullStruct",
          "ResponseType": "NullStruct",
          "ErrorResponseType": "NullStruct"
        },
        {
          "Id": 3,
          "Name": "addrow",
          "RequestType": "NullStruct",
          "ResponseType": "NullStruct",
          "ErrorResponseType": "NullStruct"
        },
        {
          "Id": 4,
          "Name": "ban",
          "RequestType": "NullStruct",
          "ResponseType": "NullStruct",
          "ErrorResponseType": "NullStruct"
        },
        {
          "Id": 5,
          "Name": "remrow",
          "RequestType": "NullStruct",
          "ResponseType": "NullStruct",
          "ErrorResponseType": "NullStruct"
        },
        {
          "Id": 9,
          "Name": "returnusers",
          "RequestType": "NullStruct",
          "ResponseType": "NullStruct",
          "ErrorResponseType": "NullStruct"
        },
        {
          "Id": 10,
          "Name": "numusers",
          "RequestType": "NullStruct",
          "ResponseType": "NullStruct",
          "ErrorResponseType": "NullStruct"
        },
        {
          "Id": 13,
          "Name": "updatenote",
          "RequestType": "NullStruct",
          "ResponseType": "NullStruct",
          "ErrorResponseType": "NullStruct"
        },
        {
          "Id": 14,
          "Name": "wipestats",
          "RequestType": "NullStruct",
          "ResponseType": "NullStruct",
          "ErrorResponseType": "NullStruct"
        },
        {
          "Id": 15,
          "Name": "updateflags",
          "RequestType": "NullStruct",
          "ResponseType": "NullStruct",
          "ErrorResponseType": "NullStruct"
        },
        {
          "Id": 16,
          "Name": "getDbCredentials",
          "RequestType": "NullStruct",
          "ResponseType": "NullStruct",
          "ErrorResponseType": "NullStruct"
        }
      ],
      "Notifications": []
    }
  ]
}